object_to_xfile/__init__.py
object_to_xfile/xconvertor.py
object_to_xfile-0.0.3.dist-info/LICENSE
object_to_xfile-0.0.3.dist-info/METADATA
object_to_xfile-0.0.3.dist-info/WHEEL
object_to_xfile-0.0.3.dist-info/top_level.txt
object_to_xfile-0.0.3.dist-info/RECORD
