Metadata-Version: 2.1
Name: object-to-xfile
Version: 0.0.3
Summary: Generate csv,xlxs,excel,pdf and html file from python dictionary objects
Home-page: UNKNOWN
Author: Sachin Indoriya
Author-email: sachinindoriya63@gmail.com
License: UNKNOWN
Keywords: python
Platform: UNKNOWN
Classifier: Development Status :: 1 - Planning
Classifier: Intended Audience :: Developers
Classifier: Programming Language :: Python :: 3
Classifier: Operating System :: Unix
Classifier: Operating System :: MacOS :: MacOS X
Classifier: Operating System :: Microsoft :: Windows
License-File: LICENSE
Requires-Dist: pandas
Requires-Dist: xml
Requires-Dist: pdfkit
Requires-Dist: flatten-json
Requires-Dist: dicttoxml
